README.md
setup.cfg
setup.py
dhtsensor/__init__.py
dhtsensor/sensor.py
dhtsensor.egg-info/PKG-INFO
dhtsensor.egg-info/SOURCES.txt
dhtsensor.egg-info/dependency_links.txt
dhtsensor.egg-info/requires.txt
dhtsensor.egg-info/top_level.txt