Metadata-Version: 2.1
Name: dhtsensor
Version: 0.2.0
Summary: Simplifies reading temperature and humidity data from a DHT11/22 sensor using pigpio
Home-page: https://github.com/kentwait/dhtsensor
Author: Kent Kawashima
Author-email: kentkawashima@gmail.com
License: UNKNOWN
Keywords: pigpio,ir,raspberry,pi,dht11,dht22
Platform: UNKNOWN
Classifier: Programming Language :: Python :: 3
Classifier: Programming Language :: Python :: 3.4
Classifier: Programming Language :: Python :: 3.5
Classifier: Programming Language :: Python :: 3.6
Classifier: License :: OSI Approved :: MIT License
Classifier: Operating System :: OS Independent
